{
  "dayKey": "2026-06-08",
  "updatedAt": "2026-06-08T23:05:25.243Z",
  "trendingIds": [
    "set-skincare-coreano-5-pasos",
    "dyson-v15-detect-absolute",
    "radiador-aceite-9-elementos",
    "masajeador-cuello-shiatsu",
    "comida-hellofresh",
    "base-carga-inalambrica-magsafe-15w",
    "mochila-antirrobo-portatil-15-6",
    "almohadilla-electrica-lumbar",
    "omega-3-1000mg-180-perlas",
    "kit-emergencia-carretera-65-piezas",
    "hot-wheels-pista-looping",
    "tp-link-tapo-camara-2k-interior",
    "cafe-grano-especial-1kg",
    "pinata-rellenable-unicornio",
    "lampara-pie-led-regulable",
    "bolsa-vacio-ropa-6u-bomba",
    "saco-dormir-bebe-invierno",
    "cable-usb-c-a-lightning-2m-mfi"
  ],
  "featuredIds": [
    "playmobil-city",
    "masajeador-cuello-shiatsu",
    "radiador-aceite-9-elementos",
    "saco-dormir-bebe-invierno",
    "aliexpress-buds",
    "protector-pantalla-cristal-9h-pack-3",
    "plancha-vapor-3000w-ceramica",
    "the-north-face-borealis-mochila"
  ],
  "dealOfDayId": "set-skincare-coreano-5-pasos"
}
